LICENSE
README.rst
setup.cfg
setup.py
plotly_svg/__init__.py
plotly_svg/_plotly_svg.py
plotly_svg.egg-info/PKG-INFO
plotly_svg.egg-info/SOURCES.txt
plotly_svg.egg-info/dependency_links.txt
plotly_svg.egg-info/requires.txt
plotly_svg.egg-info/top_level.txt