Metadata-Version: 1.1
Name: plotly-svg
Version: 0.11
Summary: Convenient way of generating vector graphics from plotly offline
Home-page: https://github.com/tech2077/plotly_svg
Author: tech2077
Author-email: tech2077@gmail.com
License: 0BSD
Download-URL: https://github.com/tech2077/plotly_svg/archive/v0.11.tar.gz
Keywords: plotly,svg,pdf
Platform: UNKNOWN
Classifier: Development Status :: 3 - Alpha
Classifier: Intended Audience :: Developers
Classifier: Topic :: Software Development :: Build Tools
Classifier: License :: OSI Approved :: BSD License
Classifier: Programming Language :: Python :: 3.5
Classifier: Programming Language :: Python :: 3.6
Classifier: Programming Language :: Python :: 3.7
